03_sequential_logic/03_sequential_logic/flip_flop.v

module d_flip_flop (
		input clk,
		input D,
		output reg Q
);

	always @(posedge clk) begin
		Q <= D;
	end

endmodule

03_sequential_logic/flip_flop_tb.v
`timescale 1ns/1ps

module d_flip_flop_tb;

	reg clk;
	reg D;
	wire Q;


d_flip_flop uut (
	.clk(clk),
	.D(D),
	.Q(Q)
);

	initial begin
		clk = 0;
	forever #2 clk = ~clk;

end


	initial begin
	$dumpfile("d_flip_flop.vcd");
	$dumpvars(0, d_flip_flop_tb);
	$display(" time | clk | D | Q |");
	$monitor(" %0t | %b | %b | %b |", $time, clk, D, Q);

		D = 0;
		#3 D = 1;
		#4 D = 0;
		#4 D = 1;
		#4 D = 0;
		#6 $finish;
	end

endmodule

03_sequential_logic/d_flip_flop.vcd
$date
	Tue Jul 21 22:57:27 2026
$end
$version
	Icarus Verilog
$end
$timescale
	1ps
$end
$scope module d_flip_flop_tb $end
$var wire 1 ! Q $end
$var reg 1 " D $end
$var reg 1 # clk $end
$scope module uut $end
$var wire 1 " D $end
$var wire 1 # clk $end
$var reg 1 ! Q $end
$upscope $end
$upscope $end
$enddefinitions $end
$comment Show the parameter values. $end
$dumpall
$end
#0
$dumpvars
0#
0"
x!
$end
#2000
0!
1#
#3000
1"
#4000
0#
#6000
1!
1#
#7000
0"
#8000
0#
#10000
0!
1#
#11000
1"
#12000
0#
#14000
1!
1#
#15000
0"
#16000
0#
#18000
0!
1#
