03_sequential_logic/debounce.v
module debounce (
    input clk,
    input rst,
    input noisy_input,
    output reg clean_output
);

    parameter THRESHOLD = 20; 

    reg [7:0] stability_counter;
    reg last_input;

    always @(posedge clk) begin
        if (rst) begin
            stability_counter <= 0;
            clean_output      <= 0;
            last_input        <= 0;
        end
        else begin
            if (noisy_input != last_input) begin
                
                stability_counter <= 0;
            end
            else if (stability_counter < THRESHOLD) begin
                
                stability_counter <= stability_counter + 1;
            end
            else begin
                ç
                clean_output <= noisy_input;
            end

            last_input <= noisy_input;
        end
    end

endmodule

03_sequential_logic/debounce_tb.v
`timescale 1ns/1ps
module debounce_tb;
    reg clk;
    reg rst;
    reg noisy_input;
    wire clean_output;

    debounce uut (
        .clk(clk),
        .rst(rst),
        .noisy_input(noisy_input),
        .clean_output(clean_output)
    );

    // Clock generator: period 10
    initial begin
        clk = 0;
        forever #5 clk = ~clk;
    end

    initial begin
        $dumpfile("debounce.vcd");
        $dumpvars(0, debounce_tb);
        $monitor(" %0t | clk=%b | rst=%b | noisy=%b | clean=%b", $time, clk, rst, noisy_input, clean_output);

        rst = 1;
        noisy_input = 0;
        #12 rst = 0;

      
        
        #8  noisy_input = 1;   // t=20  bounce start
        #8  noisy_input = 0;   // t=28  bounce
        #8  noisy_input = 1;   // t=36  bounce
        #8  noisy_input = 0;   // t=44  bounce
        #8  noisy_input = 1;   // t=52  settles high from here on

        
        #250 ;  

        
        #8  noisy_input = 0;   // bounce
        #8  noisy_input = 1;   // bounce
        #8  noisy_input = 0;   // settles low

        #250 ; 

        $finish;
    end

endmodule

03_sequential_logic/debounce.vcd
$date
	Fri Jul 24 00:54:47 2026
$end
$version
	Icarus Verilog
$end
$timescale
	1ps
$end
$scope module debounce_tb $end
$var wire 1 ! clean_output $end
$var reg 1 " clk $end
$var reg 1 # noisy_input $end
$var reg 1 $ rst $end
$scope module uut $end
$var wire 1 " clk $end
$var wire 1 # noisy_input $end
$var wire 1 $ rst $end
$var parameter 32 % THRESHOLD $end
$var reg 1 ! clean_output $end
$var reg 1 & last_input $end
$var reg 8 ' stability_counter [7:0] $end
$upscope $end
$upscope $end
$enddefinitions $end
$comment Show the parameter values. $end
$dumpall
b10100 %
$end
#0
$dumpvars
bx '
x&
1$
0#
0"
x!
$end
#5000
0&
0!
b0 '
1"
#10000
0"
#12000
0$
#15000
b1 '
1"
#20000
0"
1#
#25000
1&
b0 '
1"
#28000
0#
#30000
0"
#35000
0&
1"
#36000
1#
#40000
0"
#44000
0#
#45000
b1 '
1"
#50000
0"
#52000
1#
#55000
1&
b0 '
1"
#60000
0"
#65000
b1 '
1"
#70000
0"
#75000
b10 '
1"
#80000
0"
#85000
b11 '
1"
#90000
0"
#95000
b100 '
1"
#100000
0"
#105000
b101 '
1"
#110000
0"
#115000
b110 '
1"
#120000
0"
#125000
b111 '
1"
#130000
0"
#135000
b1000 '
1"
#140000
0"
#145000
b1001 '
1"
#150000
0"
#155000
b1010 '
1"
#160000
0"
#165000
b1011 '
1"
#170000
0"
#175000
b1100 '
1"
#180000
0"
#185000
b1101 '
1"
#190000
0"
#195000
b1110 '
1"
#200000
0"
#205000
b1111 '
1"
#210000
0"
#215000
b10000 '
1"
#220000
0"
#225000
b10001 '
1"
#230000
0"
#235000
b10010 '
1"
#240000
0"
#245000
b10011 '
1"
#250000
0"
#255000
b10100 '
1"
#260000
0"
#265000
1!
1"
#270000
0"
#275000
1"
#280000
0"
#285000
1"
#290000
0"
#295000
1"
#300000
0"
#305000
1"
#310000
0"
0#
#315000
0&
b0 '
1"
#318000
1#
#320000
0"
#325000
1&
1"
#326000
0#
#330000
0"
#335000
0&
1"
#340000
0"
#345000
b1 '
1"
#350000
0"
#355000
b10 '
1"
#360000
0"
#365000
b11 '
1"
#370000
0"
#375000
b100 '
1"
#380000
0"
#385000
b101 '
1"
#390000
0"
#395000
b110 '
1"
#400000
0"
#405000
b111 '
1"
#410000
0"
#415000
b1000 '
1"
#420000
0"
#425000
b1001 '
1"
#430000
0"
#435000
b1010 '
1"
#440000
0"
#445000
b1011 '
1"
#450000
0"
#455000
b1100 '
1"
#460000
0"
#465000
b1101 '
1"
#470000
0"
#475000
b1110 '
1"
#480000
0"
#485000
b1111 '
1"
#490000
0"
#495000
b10000 '
1"
#500000
0"
#505000
b10001 '
1"
#510000
0"
#515000
b10010 '
1"
#520000
0"
#525000
b10011 '
1"
#530000
0"
#535000
b10100 '
1"
#540000
0"
#545000
0!
1"
