smart_traffic_light/smart_traffic.v
module smart_intersection (
    input clk,
    input rst,
    input sensor_N, sensor_S, sensor_E, sensor_W,
    input ped_request,
    input [1:0] emergency_dir,

    output reg [1:0] N_light, S_light, E_light, W_light,
    output reg walk_signal
);

    
    parameter NS_GREEN    = 3'b000;
    parameter NS_YELLOW   = 3'b001;
    parameter ALL_RED     = 3'b010;
    parameter EW_GREEN    = 3'b011;
    parameter EW_YELLOW   = 3'b100;
    parameter PED_WALK    = 3'b101;
    parameter EMERGENCY   = 3'b110;

    
    parameter RED    = 2'b00;
    parameter YELLOW = 2'b01;
    parameter GREEN  = 2'b10;

    
    parameter NS_MIN_GREEN   = 10;
    parameter NS_MAX_GREEN   = 30;
    parameter EW_MIN_GREEN   = 10;
    parameter EW_MAX_GREEN   = 30;
    parameter YELLOW_DUR     = 3;
    parameter ALL_RED_DUR    = 2;
    parameter WALK_DUR       = 15;
    parameter EMERGENCY_MIN  = 8;

    
    reg [2:0] current_state, next_state;
    reg [7:0] timer;
    reg last_served;

    
    wire traffic_NS = sensor_N | sensor_S;
    wire traffic_EW = sensor_E | sensor_W;
    wire emergency_active = (emergency_dir != 2'b00);

   


    always @(posedge clk) begin
        if (rst)
            current_state <= ALL_RED;
        else
            current_state <= next_state;
    end

    
    
    always @(posedge clk) begin
        if (rst) begin
            timer <= 0;
            last_served <= 0;
        end
        else if (current_state != next_state) begin
            
            timer <= 0;
            
            if (current_state == NS_GREEN) last_served <= 0;
            if (current_state == EW_GREEN) last_served <= 1;
        end
        else begin
            timer <= timer + 1;
        end
    end

   
    
    always @(*) begin
        
        N_light = RED; S_light = RED; E_light = RED; W_light = RED;
        walk_signal = 0;

        case (current_state)
            NS_GREEN: begin
                N_light = GREEN; S_light = GREEN;
            end
            NS_YELLOW: begin
                N_light = YELLOW; S_light = YELLOW;
            end
            EW_GREEN: begin
                E_light = GREEN; W_light = GREEN;
            end
            EW_YELLOW: begin
                E_light = YELLOW; W_light = YELLOW;
            end
            PED_WALK: begin
                walk_signal = 1;   
            end
            EMERGENCY: begin
                if (emergency_dir == 2'b01) begin
                    N_light = GREEN; S_light = GREEN;
                end
                else if (emergency_dir == 2'b10) begin
                    E_light = GREEN; W_light = GREEN;
                end
            end
            
        endcase
    end

    
    always @(*) begin
        next_state = current_state; 

        
        if (emergency_active && current_state != EMERGENCY) begin
            next_state = EMERGENCY;
        end
        else begin
            case (current_state)

                NS_GREEN: begin
                    if (timer >= NS_MIN_GREEN && ped_request)
                        next_state = NS_YELLOW;
                    else if (timer >= NS_MIN_GREEN && traffic_EW && !traffic_NS)
                        next_state = NS_YELLOW;
                    else if (timer >= NS_MAX_GREEN)
                        next_state = NS_YELLOW;
                end

                NS_YELLOW: begin
                    if (timer >= YELLOW_DUR)
                        next_state = ALL_RED;
                end

                EW_GREEN: begin
                    if (timer >= EW_MIN_GREEN && ped_request)
                        next_state = EW_YELLOW;
                    else if (timer >= EW_MIN_GREEN && traffic_NS && !traffic_EW)
                        next_state = EW_YELLOW;
                    else if (timer >= EW_MAX_GREEN)
                        next_state = EW_YELLOW;
                end

                EW_YELLOW: begin
                    if (timer >= YELLOW_DUR)
                        next_state = ALL_RED;
                end

                ALL_RED: begin
                    if (timer >= ALL_RED_DUR) begin
                        if (ped_request)
                            next_state = PED_WALK;
                        else if (traffic_NS && !traffic_EW)
                            next_state = NS_GREEN;
                        else if (traffic_EW && !traffic_NS)
                            next_state = EW_GREEN;
                        else begin
                            
                            next_state = (last_served == 0) ? EW_GREEN : NS_GREEN;
                        end
                    end
                end

                PED_WALK: begin
                    if (timer >= WALK_DUR)
                        next_state = ALL_RED;
                end

                EMERGENCY: begin
                    if (!emergency_active && timer >= EMERGENCY_MIN)
                        next_state = ALL_RED;
                end

                default: next_state = ALL_RED;
            endcase
        end
    end

endmodule

smart_traffic_light/smart_traffic_tb.v
`timescale 1ns/1ps
module smart_intersection_tb;
    reg clk;
    reg rst;
    reg sensor_N, sensor_S, sensor_E, sensor_W;
    reg ped_request;
    reg [1:0] emergency_dir;

    wire [1:0] N_light, S_light, E_light, W_light;
    wire walk_signal;

    integer log_file;

    smart_intersection uut (
        .clk(clk),
        .rst(rst),
        .sensor_N(sensor_N), .sensor_S(sensor_S),
        .sensor_E(sensor_E), .sensor_W(sensor_W),
        .ped_request(ped_request),
        .emergency_dir(emergency_dir),
        .N_light(N_light), .S_light(S_light),
        .E_light(E_light), .W_light(W_light),
        .walk_signal(walk_signal)
    );

    initial begin
        clk = 0;
        forever #5 clk = ~clk;
    end

    
    always @(posedge clk) begin
        if (log_file)
            $fdisplay(log_file, "%0t,%b,%b,%b,%b,%b,%b,%b,%b,%b,%b,%b,%b",
                      $time, uut.current_state, N_light, S_light, E_light, W_light, walk_signal,
                      sensor_N, sensor_S, sensor_E, sensor_W,
                      ped_request, emergency_dir);
    end

    initial begin
        $dumpfile("smart_intersection.vcd");
        $dumpvars(0, smart_intersection_tb);

        log_file = $fopen("intersection_log.csv", "w");
        $fdisplay(log_file, "time,current_state,N_light,S_light,E_light,W_light,walk_signal,sensor_N,sensor_S,sensor_E,sensor_W,ped_request,emergency_dir");

        rst = 1;
        sensor_N = 0; sensor_S = 0; sensor_E = 0; sensor_W = 0;
        ped_request = 0;
        emergency_dir = 2'b00;
        #12 rst = 0;

        
        #8 sensor_N = 1;
        #200 ;

        
        #8 sensor_E = 1; sensor_N = 0;
        #200 ;

        
        #8 ped_request = 1;
        #300 ;             
        ped_request = 0;
        #200 ;

        
        #8 emergency_dir = 2'b01;
        #150 ;
        #8 emergency_dir = 2'b00;
        #150 ;

        $fclose(log_file);
        $finish;
    end

endmodule

smart_traffic_light/smart_intersection.vcd
$date
	Tue Jul 21 10:58:31 2026
$end
$version
	Icarus Verilog
$end
$timescale
	1ps
$end
$scope module smart_intersection_tb $end
$var wire 1 ! walk_signal $end
$var wire 2 " W_light [1:0] $end
$var wire 2 # S_light [1:0] $end
$var wire 2 $ N_light [1:0] $end
$var wire 2 % E_light [1:0] $end
$var reg 1 & clk $end
$var reg 2 ' emergency_dir [1:0] $end
$var reg 1 ( ped_request $end
$var reg 1 ) rst $end
$var reg 1 * sensor_E $end
$var reg 1 + sensor_N $end
$var reg 1 , sensor_S $end
$var reg 1 - sensor_W $end
$var integer 32 . log_file [31:0] $end
$scope module uut $end
$var wire 1 & clk $end
$var wire 2 / emergency_dir [1:0] $end
$var wire 1 ( ped_request $end
$var wire 1 ) rst $end
$var wire 1 * sensor_E $end
$var wire 1 + sensor_N $end
$var wire 1 , sensor_S $end
$var wire 1 - sensor_W $end
$var wire 1 0 traffic_EW $end
$var wire 1 1 traffic_NS $end
$var wire 1 2 emergency_active $end
$var parameter 3 3 ALL_RED $end
$var parameter 32 4 ALL_RED_DUR $end
$var parameter 3 5 EMERGENCY $end
$var parameter 32 6 EMERGENCY_MIN $end
$var parameter 3 7 EW_GREEN $end
$var parameter 32 8 EW_MAX_GREEN $end
$var parameter 32 9 EW_MIN_GREEN $end
$var parameter 3 : EW_YELLOW $end
$var parameter 2 ; GREEN $end
$var parameter 3 < NS_GREEN $end
$var parameter 32 = NS_MAX_GREEN $end
$var parameter 32 > NS_MIN_GREEN $end
$var parameter 3 ? NS_YELLOW $end
$var parameter 3 @ PED_WALK $end
$var parameter 2 A RED $end
$var parameter 32 B WALK_DUR $end
$var parameter 2 C YELLOW $end
$var parameter 32 D YELLOW_DUR $end
$var reg 2 E E_light [1:0] $end
$var reg 2 F N_light [1:0] $end
$var reg 2 G S_light [1:0] $end
$var reg 2 H W_light [1:0] $end
$var reg 3 I current_state [2:0] $end
$var reg 1 J last_served $end
$var reg 3 K next_state [2:0] $end
$var reg 8 L timer [7:0] $end
$var reg 1 ! walk_signal $end
$upscope $end
$upscope $end
$enddefinitions $end
$comment Show the parameter values. $end
$dumpall
b11 D
b1 C
b1111 B
b0 A
b101 @
b1 ?
b1010 >
b11110 =
b0 <
b10 ;
b100 :
b1010 9
b11110 8
b11 7
b1000 6
b110 5
b10 4
b10 3
$end
#0
$dumpvars
bx L
b10 K
xJ
bx I
b0 H
b0 G
b0 F
b0 E
02
01
00
b0 /
b10000000000000000000000000000011 .
0-
0,
0+
0*
1)
0(
b0 '
0&
b0 %
b0 $
b0 #
b0 "
0!
$end
#5000
b10 I
0J
b0 L
1&
#10000
0&
#12000
0)
#15000
b1 L
1&
#20000
11
0&
1+
#25000
b0 K
b10 L
1&
#30000
0&
#35000
b10 #
b10 G
b10 $
b10 F
b0 L
b0 I
1&
#40000
0&
#45000
b1 L
1&
#50000
0&
#55000
b10 L
1&
#60000
0&
#65000
b11 L
1&
#70000
0&
#75000
b100 L
1&
#80000
0&
#85000
b101 L
1&
#90000
0&
#95000
b110 L
1&
#100000
0&
#105000
b111 L
1&
#110000
0&
#115000
b1000 L
1&
#120000
0&
#125000
b1001 L
1&
#130000
0&
#135000
b1010 L
1&
#140000
0&
#145000
b1011 L
1&
#150000
0&
#155000
b1100 L
1&
#160000
0&
#165000
b1101 L
1&
#170000
0&
#175000
b1110 L
1&
#180000
0&
#185000
b1111 L
1&
#190000
0&
#195000
b10000 L
1&
#200000
0&
#205000
b10001 L
1&
#210000
0&
#215000
b10010 L
1&
#220000
0&
#225000
b10011 L
1&
#228000
b1 K
01
10
0+
1*
#230000
0&
#235000
b1 #
b1 G
b1 $
b1 F
b0 L
b1 I
1&
#240000
0&
#245000
b1 L
1&
#250000
0&
#255000
b10 L
1&
#260000
0&
#265000
b10 K
b11 L
1&
#270000
0&
#275000
b0 #
b0 G
b0 $
b0 F
b0 L
b10 I
1&
#280000
0&
#285000
b1 L
1&
#290000
0&
#295000
b11 K
b10 L
1&
#300000
0&
#305000
b10 "
b10 H
b10 %
b10 E
b11 I
b0 L
1&
#310000
0&
#315000
b1 L
1&
#320000
0&
#325000
b10 L
1&
#330000
0&
#335000
b11 L
1&
#340000
0&
#345000
b100 L
1&
#350000
0&
#355000
b101 L
1&
#360000
0&
#365000
b110 L
1&
#370000
0&
#375000
b111 L
1&
#380000
0&
#385000
b1000 L
1&
#390000
0&
#395000
b1001 L
1&
#400000
0&
#405000
b1010 L
1&
#410000
0&
#415000
b1011 L
1&
#420000
0&
#425000
b1100 L
1&
#430000
0&
#435000
b1101 L
1&
#436000
b100 K
1(
#440000
0&
#445000
b1 "
b1 H
b1 %
b1 E
b100 I
1J
b0 L
1&
#450000
0&
#455000
b1 L
1&
#460000
0&
#465000
b10 L
1&
#470000
0&
#475000
b10 K
b11 L
1&
#480000
0&
#485000
b0 "
b0 H
b0 %
b0 E
b10 I
b0 L
1&
#490000
0&
#495000
b1 L
1&
#500000
0&
#505000
b101 K
b10 L
1&
#510000
0&
#515000
1!
b0 L
b101 I
1&
#520000
0&
#525000
b1 L
1&
#530000
0&
#535000
b10 L
1&
#540000
0&
#545000
b11 L
1&
#550000
0&
#555000
b100 L
1&
#560000
0&
#565000
b101 L
1&
#570000
0&
#575000
b110 L
1&
#580000
0&
#585000
b111 L
1&
#590000
0&
#595000
b1000 L
1&
#600000
0&
#605000
b1001 L
1&
#610000
0&
#615000
b1010 L
1&
#620000
0&
#625000
b1011 L
1&
#630000
0&
#635000
b1100 L
1&
#640000
0&
#645000
b1101 L
1&
#650000
0&
#655000
b1110 L
1&
#660000
0&
#665000
b10 K
b1111 L
1&
#670000
0&
#675000
0!
b0 L
b10 I
1&
#680000
0&
#685000
b1 L
1&
#690000
0&
#695000
b101 K
b10 L
1&
#700000
0&
#705000
1!
b101 I
b0 L
1&
#710000
0&
#715000
b1 L
1&
#720000
0&
#725000
b10 L
1&
#730000
0&
#735000
b11 L
1&
#736000
0(
#740000
0&
#745000
b100 L
1&
#750000
0&
#755000
b101 L
1&
#760000
0&
#765000
b110 L
1&
#770000
0&
#775000
b111 L
1&
#780000
0&
#785000
b1000 L
1&
#790000
0&
#795000
b1001 L
1&
#800000
0&
#805000
b1010 L
1&
#810000
0&
#815000
b1011 L
1&
#820000
0&
#825000
b1100 L
1&
#830000
0&
#835000
b1101 L
1&
#840000
0&
#845000
b1110 L
1&
#850000
0&
#855000
b10 K
b1111 L
1&
#860000
0&
#865000
0!
b10 I
b0 L
1&
#870000
0&
#875000
b1 L
1&
#880000
0&
#885000
b11 K
b10 L
1&
#890000
0&
#895000
b10 "
b10 H
b10 %
b10 E
b0 L
b11 I
1&
#900000
0&
#905000
b1 L
1&
#910000
0&
#915000
b10 L
1&
#920000
0&
#925000
b11 L
1&
#930000
0&
#935000
b100 L
1&
#940000
0&
#944000
b10 "
b10 H
b10 %
b10 E
b110 K
12
b1 '
b1 /
#945000
b10 #
b10 G
b10 $
b10 F
b0 "
b0 H
b0 %
b0 E
b110 I
b0 L
1&
#950000
0&
#955000
b1 L
1&
#960000
0&
#965000
b10 L
1&
#970000
0&
#975000
b11 L
1&
#980000
0&
#985000
b100 L
1&
#990000
0&
#995000
b101 L
1&
#1000000
0&
#1005000
b110 L
1&
#1010000
0&
#1015000
b111 L
1&
#1020000
0&
#1025000
b1000 L
1&
#1030000
0&
#1035000
b1001 L
1&
#1040000
0&
#1045000
b1010 L
1&
#1050000
0&
#1055000
b1011 L
1&
#1060000
0&
#1065000
b1100 L
1&
#1070000
0&
#1075000
b1101 L
1&
#1080000
0&
#1085000
b1110 L
1&
#1090000
0&
#1095000
b1111 L
1&
#1100000
0&
#1102000
b0 #
b0 G
b0 $
b0 F
b10 K
02
b0 '
b0 /
#1105000
b10 I
b0 L
1&
#1110000
0&
#1115000
b1 L
1&
#1120000
0&
#1125000
b11 K
b10 L
1&
#1130000
0&
#1135000
b10 "
b10 H
b10 %
b10 E
b0 L
b11 I
1&
#1140000
0&
#1145000
b1 L
1&
#1150000
0&
#1155000
b10 L
1&
#1160000
0&
#1165000
b11 L
1&
#1170000
0&
#1175000
b100 L
1&
#1180000
0&
#1185000
b101 L
1&
#1190000
0&
#1195000
b110 L
1&
#1200000
0&
#1205000
b111 L
1&
#1210000
0&
#1215000
b1000 L
1&
#1220000
0&
#1225000
b1001 L
1&
#1230000
0&
#1235000
b1010 L
1&
#1240000
0&
#1245000
b1011 L
1&
