02_combinational_logic/adder/full_adder/full_adder.v
module full_adder (

	input a,
	input b,
	input Cin,
	output sum,
	output Cout
);
	

	assign sum = a ^ b ^ Cin;
	assign Cout = a & b | a & Cin | b & Cin;

endmodule

02_combinational_logic/adder/full_adder/full_adder_tb.v
`timescale 1ns/1ps

module full_adder_tb;

	reg a, b, Cin;
	wire sum, Cout;


	full_adder uut (
		.a(a),
		.b(b),
		.Cin(Cin),
		.sum(sum),
		.Cout(Cout)
);

	initial begin

	$dumpfile("full_adder.vcd");
	$dumpvars(0, full_adder_tb);
	

	$display(" A | B | Cin | sum | Cout");

	a = 0; b = 0; Cin = 0; #10;
	$display(" %b | %b | %b | %b | %b ", a, b, Cin, sum, Cout);

	a = 0; b = 0; Cin = 1; #10;
	$display(" %b | %b | %b | %b | %b ", a, b, Cin, sum, Cout);

	a = 0; b = 1; Cin = 0; #10;
	$display(" %b | %b | %b | %b | %b ", a, b, Cin, sum, Cout);

	a = 0; b = 1; Cin = 1; #10;
	$display(" %b | %b | %b | %b | %b ", a, b, Cin, sum, Cout);

	a = 1; b = 0; Cin = 0; #10;
	$display(" %b | %b | %b | %b | %b ", a, b, Cin, sum, Cout);

	a = 1; b = 0; Cin = 1; #10;
	$display(" %b | %b | %b | %b | %b ", a, b, Cin, sum, Cout);

	a = 1; b = 1; Cin = 0; #10;
	$display(" %b | %b | %b | %b | %b ", a, b, Cin, sum, Cout);

	a = 1; b = 1; Cin = 1; #10;
	$display(" %b | %b | %b | %b | %b ", a, b, Cin, sum, Cout);

$finish;

end

endmodule

02_combinational_logic/adder/full_adder/full_adder.vcd
$date
	Wed Jun 24 10:47:17 2026
$end
$version
	Icarus Verilog
$end
$timescale
	1ps
$end
$scope module full_adder_tb $end
$var wire 1 ! sum $end
$var wire 1 " Cout $end
$var reg 1 # Cin $end
$var reg 1 $ a $end
$var reg 1 % b $end
$scope module uut $end
$var wire 1 # Cin $end
$var wire 1 " Cout $end
$var wire 1 $ a $end
$var wire 1 % b $end
$var wire 1 ! sum $end
$upscope $end
$upscope $end
$enddefinitions $end
$comment Show the parameter values. $end
$dumpall
$end
#0
$dumpvars
0%
0$
0#
0"
0!
$end
#10000
1!
1#
#20000
0#
1%
#30000
1"
0!
1#
#40000
0"
1!
0#
0%
1$
#50000
1"
0!
1#
#60000
0#
1%
#70000
1!
1#
