FSM/ped_traffic_light.v
module ped_traffic_light(
	input clk,
	input rst,
	input ped_button_pressed,	
	output reg [1:0] light,
	output reg walk_signal
);

	parameter RED    = 2'b00;
	parameter GREEN  = 2'b01;
	parameter YELLOW = 2'b10;
	parameter WALK   = 2'b11;

	parameter LIGHT_RED    = 2'b00;
	parameter LIGHT_GREEN  = 2'b01;
	parameter LIGHT_YELLOW = 2'b10;

	parameter RED_DURATION       = 20;
	parameter GREEN_MIN_DURATION = 15;
	parameter GREEN_MAX_DURATION = 40;
	parameter YELLOW_DURATION    = 5;
	parameter WALK_DURATION      = 15;

	reg [1:0] current_state, next_state;
	reg [7:0] timer;
	reg ped_request;


	always @(posedge clk) begin
		if (rst)
			current_state  <= RED;
		else
			current_state <= next_state;
	end

	

	always @(posedge clk) begin
		if (rst) begin
			timer <= 0;
			ped_request <= 0;
	end

	else if (current_state != next_state) begin
		timer <= 0;
	if (next_state == GREEN)
		ped_request <= 0;
	end
	else begin
		timer <= timer + 1;
	if (current_state == GREEN && ped_button_pressed)
		ped_request <= 1;
	end
end

	always @(*) begin
		light       = LIGHT_RED;
		walk_signal = 0;

	case (current_state)
		RED: light = LIGHT_RED;
		GREEN: light = LIGHT_GREEN;
		YELLOW: light = LIGHT_YELLOW;
		WALK: begin
			light  = LIGHT_RED;
			walk_signal = 1;
		end
	endcase
end


	always @(*) begin
		next_state = current_state;
		
		case (current_state)
            RED: begin
                if (timer == RED_DURATION)
                    next_state = GREEN;
            end

            GREEN: begin
                if (timer >= GREEN_MIN_DURATION && ped_request)
                    next_state = YELLOW;
                else if (timer == GREEN_MAX_DURATION)
                    next_state = YELLOW;
            end

            YELLOW: begin
                if (timer == YELLOW_DURATION)
                    next_state = WALK;
            end

            WALK: begin
                if (timer == WALK_DURATION)
                    next_state = RED;
            end

            default: next_state = RED;
        endcase
    end

endmodule

FSM/ped_traffic_light_tb.v
`timescale 1ns/1ps

module ped_traffic_light_tb;

	reg clk;
	reg rst;
	reg ped_button_pressed;
	wire [1:0] light;
	wire walk_signal;

ped_traffic_light uut(
	.clk(clk),
	.rst(rst),
	.ped_button_pressed(ped_button_pressed),
	.light(light),
	.walk_signal(walk_signal)
);

	initial begin
	clk = 0;
	forever #5 clk = ~clk;
end

	initial begin
	$dumpfile("ped_traffic_light.vcd");
	$dumpvars(0, ped_traffic_light_tb);
	$monitor("%0t | clk=%b | rst=%b | state=%b | light=%b | walk=%b | button=%b |", $time, clk, rst,  uut.current_state, light, walk_signal, ped_button_pressed);

	rst = 1;
	ped_button_pressed = 0;
	#12 rst = 0;


	#210;


	#8 ped_button_pressed = 1;
	#10 ped_button_pressed = 0;
	#300;


	$finish;
end

endmodule

FSM/ped_traffic_light.vcd
$date
	Tue Jul 28 00:10:05 2026
$end
$version
	Icarus Verilog
$end
$timescale
	1ps
$end
$scope module ped_traffic_light_tb $end
$var wire 1 ! walk_signal $end
$var wire 2 " light [1:0] $end
$var reg 1 # clk $end
$var reg 1 $ ped_button_pressed $end
$var reg 1 % rst $end
$scope module uut $end
$var wire 1 # clk $end
$var wire 1 $ ped_button_pressed $end
$var wire 1 % rst $end
$var parameter 2 & GREEN $end
$var parameter 32 ' GREEN_MAX_DURATION $end
$var parameter 32 ( GREEN_MIN_DURATION $end
$var parameter 2 ) LIGHT_GREEN $end
$var parameter 2 * LIGHT_RED $end
$var parameter 2 + LIGHT_YELLOW $end
$var parameter 2 , RED $end
$var parameter 32 - RED_DURATION $end
$var parameter 2 . WALK $end
$var parameter 32 / WALK_DURATION $end
$var parameter 2 0 YELLOW $end
$var parameter 32 1 YELLOW_DURATION $end
$var reg 2 2 current_state [1:0] $end
$var reg 2 3 light [1:0] $end
$var reg 2 4 next_state [1:0] $end
$var reg 1 5 ped_request $end
$var reg 8 6 timer [7:0] $end
$var reg 1 ! walk_signal $end
$upscope $end
$upscope $end
$enddefinitions $end
$comment Show the parameter values. $end
$dumpall
b101 1
b10 0
b1111 /
b11 .
b10100 -
b0 ,
b10 +
b0 *
b1 )
b1111 (
b101000 '
b1 &
$end
#0
$dumpvars
bx 6
x5
bx 4
bx 3
bx 2
1%
0$
0#
bx "
x!
$end
#5000
0!
b0 "
b0 3
b0 4
b0 2
05
b0 6
1#
#10000
0#
#12000
0%
#15000
b1 6
1#
#20000
0#
#25000
b10 6
1#
#30000
0#
#35000
b11 6
1#
#40000
0#
#45000
b100 6
1#
#50000
0#
#55000
b101 6
1#
#60000
0#
#65000
b110 6
1#
#70000
0#
#75000
b111 6
1#
#80000
0#
#85000
b1000 6
1#
#90000
0#
#95000
b1001 6
1#
#100000
0#
#105000
b1010 6
1#
#110000
0#
#115000
b1011 6
1#
#120000
0#
#125000
b1100 6
1#
#130000
0#
#135000
b1101 6
1#
#140000
0#
#145000
b1110 6
1#
#150000
0#
#155000
b1111 6
1#
#160000
0#
#165000
b10000 6
1#
#170000
0#
#175000
b10001 6
1#
#180000
0#
#185000
b10010 6
1#
#190000
0#
#195000
b10011 6
1#
#200000
0#
#205000
b1 4
b10100 6
1#
#210000
0#
#215000
b1 "
b1 3
b0 6
b1 2
1#
#220000
0#
#225000
b1 6
1#
#230000
0#
1$
#235000
15
b10 6
1#
#240000
0#
0$
#245000
b11 6
1#
#250000
0#
#255000
b100 6
1#
#260000
0#
#265000
b101 6
1#
#270000
0#
#275000
b110 6
1#
#280000
0#
#285000
b111 6
1#
#290000
0#
#295000
b1000 6
1#
#300000
0#
#305000
b1001 6
1#
#310000
0#
#315000
b1010 6
1#
#320000
0#
#325000
b1011 6
1#
#330000
0#
#335000
b1100 6
1#
#340000
0#
#345000
b1101 6
1#
#350000
0#
#355000
b1110 6
1#
#360000
0#
#365000
b10 4
b1111 6
1#
#370000
0#
#375000
b10 "
b10 3
b0 6
b10 2
1#
#380000
0#
#385000
b1 6
1#
#390000
0#
#395000
b10 6
1#
#400000
0#
#405000
b11 6
1#
#410000
0#
#415000
b100 6
1#
#420000
0#
#425000
b11 4
b101 6
1#
#430000
0#
#435000
1!
b0 "
b0 3
b0 6
b11 2
1#
#440000
0#
#445000
b1 6
1#
#450000
0#
#455000
b10 6
1#
#460000
0#
#465000
b11 6
1#
#470000
0#
#475000
b100 6
1#
#480000
0#
#485000
b101 6
1#
#490000
0#
#495000
b110 6
1#
#500000
0#
#505000
b111 6
1#
#510000
0#
#515000
b1000 6
1#
#520000
0#
#525000
b1001 6
1#
#530000
0#
#535000
b1010 6
1#
