FSM/two_road_intersection.v
module two_road_intersection (
	input clk,
	input rst,
	input sensor_A,
	input sensor_B,
	output reg [1:0] roadA_light,
	output reg [1:0] roadB_light
);

	parameter A_GREEN = 3'b000;
	parameter A_YELLOW = 3'b001;
	parameter ALL_RED = 3'b010;
	parameter B_GREEN = 3'b011;
	parameter B_YELLOW = 3'b100;

	parameter RED = 2'b00;
	parameter YELLOW = 2'b01;
	parameter GREEN = 2'b10;

	parameter A_MIN_GREEN = 15;
	parameter A_MAX_GREEN = 40;
	parameter B_MIN_GREEN = 15;
	parameter B_MAX_GREEN = 40;
	parameter YELLOW_DUR  = 5;
	parameter ALL_RED_DUR = 3;

	reg [2:0] current_state, next_state;
	reg [7:0] timer;
	reg last_served;

	always @(posedge clk) begin
		if (rst)
			current_state <= ALL_RED;
		else
			current_state <= next_state;
	end


	always @(posedge clk) begin
		if (rst) begin
			timer <= 0;
			last_served <= 0;
		end
		else if (current_state != next_state) begin
			timer <= 0;
			if (current_state == A_GREEN) last_served <= 0;
			if (current_state == B_GREEN) last_served <= 1;
		end
		else begin
			timer <= timer + 1;
		end
	end

	

	always @(*) begin
		roadA_light = RED;
		roadB_light = RED;

		case (current_state)
			A_GREEN: roadA_light  = GREEN;
			A_YELLOW: roadA_light = YELLOW;
			B_GREEN: roadB_light  = GREEN;
			B_YELLOW: roadB_light = YELLOW;
		endcase
	end

	always @(*) begin
		next_state = current_state;

		case (current_state)
			A_GREEN: begin
				if (timer >= A_MIN_GREEN && sensor_B && !sensor_A)
					next_state = A_YELLOW;
				else if (timer >= A_MAX_GREEN)
					next_state = A_YELLOW;
			end

			A_YELLOW: begin
				if (timer >= YELLOW_DUR)
					next_state = ALL_RED;
			end

			ALL_RED: begin
				if (timer >= ALL_RED_DUR) begin
					if (sensor_A && !sensor_B)
						next_state = A_GREEN;
					else if (sensor_B && !sensor_A)
						next_state = B_GREEN;
					else
						next_state = (last_served == 0) ? B_GREEN : A_GREEN;
				end
			end

			B_GREEN: begin
				if (timer >= B_MIN_GREEN && sensor_A && !sensor_B)
					next_state = B_YELLOW;
				else if (timer >= B_MAX_GREEN)
					next_state = B_YELLOW;
			end

			B_YELLOW: begin
				if (timer >= YELLOW_DUR)
					next_state = ALL_RED;
			end

			default: next_state = ALL_RED;
		endcase
	end
endmodule

FSM/two_road_intersection_tb.v
`timescale 1ns/1ps

module two_road_intersection_tb;
	reg clk;
	reg rst;
	reg sensor_A;
	reg sensor_B;
	wire [1:0] roadA_light;
	wire [1:0] roadB_light;

two_road_intersection uut (
	.clk(clk),
	.rst(rst),
	.sensor_A(sensor_A),
	.sensor_B(sensor_B),
	.roadA_light(roadA_light),
	.roadB_light(roadB_light)
);

	initial begin
		clk = 0;
	forever #5 clk = ~clk;
end

	initial begin
$dumpfile("two_road_intersection.vcd");
$dumpvars(0, two_road_intersection_tb);
$monitor("%0t | clk=%b | rst=%b | state=%b | A_light=%b | B_light=%b | sensorA=%b | sensorB=%b |", $time, clk, rst, uut.current_state, roadA_light, roadB_light, sensor_A, sensor_B);

	rst = 1;
	sensor_A = 0; 
	sensor_B = 0;
	#12 rst = 0;



	#8 sensor_A = 1;
	#300;


	#8 sensor_B = 1;
	#8 sensor_A = 0;
	#300;


	#8 sensor_A = 1;
	#500;

	#8 sensor_A = 0;
	#8 sensor_B = 0;
	#500;

	#8 sensor_A = 0;
	#8 sensor_B = 0;
	#500;

	$finish;
end

endmodule

FSM/two_road_intersection.vcd
$date
	Thu Jul 30 23:25:22 2026
$end
$version
	Icarus Verilog
$end
$timescale
	1ps
$end
$scope module two_road_intersection_tb $end
$var wire 2 ! roadB_light [1:0] $end
$var wire 2 " roadA_light [1:0] $end
$var reg 1 # clk $end
$var reg 1 $ rst $end
$var reg 1 % sensor_A $end
$var reg 1 & sensor_B $end
$scope module uut $end
$var wire 1 # clk $end
$var wire 1 $ rst $end
$var wire 1 % sensor_A $end
$var wire 1 & sensor_B $end
$var parameter 3 ' ALL_RED $end
$var parameter 32 ( ALL_RED_DUR $end
$var parameter 3 ) A_GREEN $end
$var parameter 32 * A_MAX_GREEN $end
$var parameter 32 + A_MIN_GREEN $end
$var parameter 3 , A_YELLOW $end
$var parameter 3 - B_GREEN $end
$var parameter 32 . B_MAX_GREEN $end
$var parameter 32 / B_MIN_GREEN $end
$var parameter 3 0 B_YELLOW $end
$var parameter 2 1 GREEN $end
$var parameter 2 2 RED $end
$var parameter 2 3 YELLOW $end
$var parameter 32 4 YELLOW_DUR $end
$var reg 3 5 current_state [2:0] $end
$var reg 1 6 last_served $end
$var reg 3 7 next_state [2:0] $end
$var reg 2 8 roadA_light [1:0] $end
$var reg 2 9 roadB_light [1:0] $end
$var reg 8 : timer [7:0] $end
$upscope $end
$upscope $end
$enddefinitions $end
$comment Show the parameter values. $end
$dumpall
b101 4
b1 3
b0 2
b10 1
b100 0
b1111 /
b101000 .
b11 -
b1 ,
b1111 +
b101000 *
b0 )
b11 (
b10 '
$end
#0
$dumpvars
bx :
bx 9
bx 8
b10 7
x6
bx 5
0&
0%
1$
0#
bx "
bx !
$end
#5000
b0 !
b0 9
b0 "
b0 8
b10 5
06
b0 :
1#
#10000
0#
#12000
0$
#15000
b1 :
1#
#20000
0#
1%
#25000
b10 :
1#
#30000
0#
#35000
b0 7
b11 :
1#
#40000
0#
#45000
b10 "
b10 8
b0 5
b0 :
1#
#50000
0#
#55000
b1 :
1#
#60000
0#
#65000
b10 :
1#
#70000
0#
#75000
b11 :
1#
#80000
0#
#85000
b100 :
1#
#90000
0#
#95000
b101 :
1#
#100000
0#
#105000
b110 :
1#
#110000
0#
#115000
b111 :
1#
#120000
0#
#125000
b1000 :
1#
#130000
0#
#135000
b1001 :
1#
#140000
0#
#145000
b1010 :
1#
#150000
0#
#155000
b1011 :
1#
#160000
0#
#165000
b1100 :
1#
#170000
0#
#175000
b1101 :
1#
#180000
0#
#185000
b1110 :
1#
#190000
0#
#195000
b1111 :
1#
#200000
0#
#205000
b10000 :
1#
#210000
0#
#215000
b10001 :
1#
#220000
0#
#225000
b10010 :
1#
#230000
0#
#235000
b10011 :
1#
#240000
0#
#245000
b10100 :
1#
#250000
0#
#255000
b10101 :
1#
#260000
0#
#265000
b10110 :
1#
#270000
0#
#275000
b10111 :
1#
#280000
0#
#285000
b11000 :
1#
#290000
0#
#295000
b11001 :
1#
#300000
0#
#305000
b11010 :
1#
#310000
0#
#315000
b11011 :
1#
#320000
0#
#325000
b11100 :
1#
#328000
1&
#330000
0#
#335000
b11101 :
1#
#336000
b1 7
0%
#340000
0#
#345000
b1 "
b1 8
b1 5
b0 :
1#
#350000
0#
#355000
b1 :
1#
#360000
0#
#365000
b10 :
1#
#370000
0#
#375000
b11 :
1#
#380000
0#
#385000
b100 :
1#
#390000
0#
#395000
b10 7
b101 :
1#
#400000
0#
#405000
b0 "
b0 8
b10 5
b0 :
1#
#410000
0#
#415000
b1 :
1#
#420000
0#
#425000
b10 :
1#
#430000
0#
#435000
b11 7
b11 :
1#
#440000
0#
#445000
b10 !
b10 9
b11 5
b0 :
1#
#450000
0#
#455000
b1 :
1#
#460000
0#
#465000
b10 :
1#
#470000
0#
#475000
b11 :
1#
#480000
0#
#485000
b100 :
1#
#490000
0#
#495000
b101 :
1#
#500000
0#
#505000
b110 :
1#
#510000
0#
#515000
b111 :
1#
#520000
0#
#525000
b1000 :
1#
#530000
0#
#535000
b1001 :
1#
#540000
0#
#545000
b1010 :
1#
#550000
0#
#555000
b1011 :
1#
#560000
0#
#565000
b1100 :
1#
#570000
0#
#575000
b1101 :
1#
#580000
0#
#585000
b1110 :
1#
#590000
0#
#595000
b1111 :
1#
#600000
0#
#605000
b10000 :
1#
#610000
0#
#615000
b10001 :
1#
#620000
0#
#625000
b10010 :
1#
#630000
0#
#635000
b10011 :
1#
#640000
0#
#644000
1%
#645000
b10100 :
1#
#650000
0#
#655000
b10101 :
1#
#660000
0#
#665000
b10110 :
1#
#670000
0#
#675000
b10111 :
1#
#680000
0#
#685000
b11000 :
1#
#690000
0#
#695000
b11001 :
1#
#700000
0#
#705000
b11010 :
1#
#710000
0#
#715000
b11011 :
1#
#720000
0#
#725000
b11100 :
1#
#730000
0#
#735000
b11101 :
1#
#740000
0#
#745000
b11110 :
1#
#750000
0#
#755000
b11111 :
1#
#760000
0#
#765000
b100000 :
1#
#770000
0#
#775000
b100001 :
1#
#780000
0#
#785000
b100010 :
1#
#790000
0#
#795000
b100011 :
1#
#800000
0#
#805000
b100100 :
1#
#810000
0#
#815000
b100101 :
1#
#820000
0#
#825000
b100110 :
1#
#830000
0#
#835000
b100111 :
1#
#840000
0#
#845000
b100 7
b101000 :
1#
#850000
0#
#855000
b1 !
b1 9
16
b0 :
b100 5
1#
#860000
0#
#865000
b1 :
1#
#870000
0#
#875000
b10 :
1#
#880000
0#
#885000
b11 :
1#
#890000
0#
#895000
b100 :
1#
#900000
0#
#905000
b10 7
b101 :
1#
#910000
0#
#915000
b0 !
b0 9
b0 :
b10 5
1#
#920000
0#
#925000
b1 :
1#
#930000
0#
#935000
b10 :
1#
#940000
0#
#945000
b0 7
b11 :
1#
#950000
0#
#955000
b10 "
b10 8
b0 :
b0 5
1#
#960000
0#
#965000
b1 :
1#
#970000
0#
#975000
b10 :
1#
#980000
0#
#985000
b11 :
1#
#990000
0#
#995000
b100 :
1#
#1000000
0#
#1005000
b101 :
1#
#1010000
0#
#1015000
b110 :
1#
#1020000
0#
#1025000
b111 :
1#
#1030000
0#
#1035000
b1000 :
1#
#1040000
0#
#1045000
b1001 :
1#
#1050000
0#
#1055000
b1010 :
1#
#1060000
0#
#1065000
b1011 :
1#
#1070000
0#
#1075000
b1100 :
1#
#1080000
0#
#1085000
b1101 :
1#
#1090000
0#
#1095000
b1110 :
1#
#1100000
0#
#1105000
b1111 :
1#
#1110000
0#
#1115000
b10000 :
1#
#1120000
0#
#1125000
b10001 :
1#
#1130000
0#
#1135000
b10010 :
1#
#1140000
0#
#1145000
b10011 :
1#
#1150000
0#
#1152000
b1 7
0%
#1155000
b1 "
b1 8
06
b0 :
b1 5
1#
#1160000
0#
0&
#1165000
b1 :
1#
#1170000
0#
#1175000
b10 :
1#
#1180000
0#
#1185000
b11 :
1#
#1190000
0#
#1195000
b100 :
1#
#1200000
0#
#1205000
b10 7
b101 :
1#
#1210000
0#
#1215000
b0 "
b0 8
b0 :
b10 5
1#
#1220000
0#
#1225000
b1 :
1#
#1230000
0#
#1235000
b10 :
1#
#1240000
0#
#1245000
b11 7
b11 :
1#
#1250000
0#
#1255000
b10 !
b10 9
b0 :
b11 5
1#
#1260000
0#
#1265000
b1 :
1#
#1270000
0#
#1275000
b10 :
1#
#1280000
0#
#1285000
b11 :
1#
#1290000
0#
#1295000
b100 :
1#
#1300000
0#
#1305000
b101 :
1#
#1310000
0#
#1315000
b110 :
1#
#1320000
0#
#1325000
b111 :
1#
#1330000
0#
#1335000
b1000 :
1#
#1340000
0#
#1345000
b1001 :
1#
#1350000
0#
#1355000
b1010 :
1#
#1360000
0#
#1365000
b1011 :
1#
#1370000
0#
#1375000
b1100 :
1#
#1380000
0#
#1385000
b1101 :
1#
#1390000
0#
#1395000
b1110 :
1#
#1400000
0#
#1405000
b1111 :
1#
#1410000
0#
#1415000
b10000 :
1#
#1420000
0#
#1425000
b10001 :
1#
#1430000
0#
#1435000
b10010 :
1#
#1440000
0#
#1445000
b10011 :
1#
#1450000
0#
#1455000
b10100 :
1#
#1460000
0#
#1465000
b10101 :
1#
#1470000
0#
#1475000
b10110 :
1#
#1480000
0#
#1485000
b10111 :
1#
#1490000
0#
#1495000
b11000 :
1#
#1500000
0#
#1505000
b11001 :
1#
#1510000
0#
#1515000
b11010 :
1#
#1520000
0#
#1525000
b11011 :
1#
#1530000
0#
#1535000
b11100 :
1#
#1540000
0#
#1545000
b11101 :
1#
#1550000
0#
#1555000
b11110 :
1#
#1560000
0#
#1565000
b11111 :
1#
#1570000
0#
#1575000
b100000 :
1#
#1580000
0#
#1585000
b100001 :
1#
#1590000
0#
#1595000
b100010 :
1#
#1600000
0#
#1605000
b100011 :
1#
#1610000
0#
#1615000
b100100 :
1#
#1620000
0#
#1625000
b100101 :
1#
#1630000
0#
#1635000
b100110 :
1#
#1640000
0#
#1645000
b100111 :
1#
#1650000
0#
#1655000
b100 7
b101000 :
1#
#1660000
0#
#1665000
b1 !
b1 9
b100 5
16
b0 :
1#
#1670000
0#
#1675000
b1 :
1#
#1680000
0#
#1685000
b10 :
1#
#1690000
0#
#1695000
b11 :
1#
#1700000
0#
#1705000
b100 :
1#
#1710000
0#
#1715000
b10 7
b101 :
1#
#1720000
0#
#1725000
b0 !
b0 9
b10 5
b0 :
1#
#1730000
0#
#1735000
b1 :
1#
#1740000
0#
#1745000
b10 :
1#
#1750000
0#
#1755000
b0 7
b11 :
1#
#1760000
0#
#1765000
b10 "
b10 8
b0 5
b0 :
1#
#1770000
0#
#1775000
b1 :
1#
#1780000
0#
#1785000
b10 :
1#
#1790000
0#
#1795000
b11 :
1#
#1800000
0#
#1805000
b100 :
1#
#1810000
0#
#1815000
b101 :
1#
#1820000
0#
#1825000
b110 :
1#
#1830000
0#
#1835000
b111 :
1#
#1840000
0#
#1845000
b1000 :
1#
#1850000
0#
#1855000
b1001 :
1#
#1860000
0#
#1865000
b1010 :
1#
#1870000
0#
#1875000
b1011 :
1#
#1880000
0#
#1885000
b1100 :
1#
#1890000
0#
#1895000
b1101 :
1#
#1900000
0#
#1905000
b1110 :
1#
#1910000
0#
#1915000
b1111 :
1#
#1920000
0#
#1925000
b10000 :
1#
#1930000
0#
#1935000
b10001 :
1#
#1940000
0#
#1945000
b10010 :
1#
#1950000
0#
#1955000
b10011 :
1#
#1960000
0#
#1965000
b10100 :
1#
#1970000
0#
#1975000
b10101 :
1#
#1980000
0#
#1985000
b10110 :
1#
#1990000
0#
#1995000
b10111 :
1#
#2000000
0#
#2005000
b11000 :
1#
#2010000
0#
#2015000
b11001 :
1#
#2020000
0#
#2025000
b11010 :
1#
#2030000
0#
#2035000
b11011 :
1#
#2040000
0#
#2045000
b11100 :
1#
#2050000
0#
#2055000
b11101 :
1#
#2060000
0#
#2065000
b11110 :
1#
#2070000
0#
#2075000
b11111 :
1#
#2080000
0#
#2085000
b100000 :
1#
#2090000
0#
#2095000
b100001 :
1#
#2100000
0#
#2105000
b100010 :
1#
#2110000
0#
#2115000
b100011 :
1#
#2120000
0#
#2125000
b100100 :
1#
#2130000
0#
#2135000
b100101 :
1#
#2140000
0#
#2145000
b100110 :
1#
#2150000
0#
#2155000
b100111 :
1#
#2160000
0#
#2165000
b1 7
b101000 :
1#
#2170000
0#
#2175000
b1 "
b1 8
06
b0 :
b1 5
1#
