FSM/uart.v
module uart ( 
	input clk,
	input rst,
	input start_send,
	input [7:0] data_byte,
	output reg tx_line
);

	parameter IDLE = 2'b00;
	parameter START = 2'b01;
	parameter DATA = 2'b10;
	parameter STOP = 2'b11;

	reg [1:0] current_state, next_state;
	reg [2:0] bit_counter;
	reg [7:0] data_reg;

	always @(posedge clk) begin
		if (rst)
			current_state <= IDLE;
		else
			current_state <= next_state;
end


	always @(posedge clk) begin
		if (rst) begin
			bit_counter <= 0;
			data_reg    <= 0;
			tx_line     <= 1'b1;
	end
	else begin
		case (current_state)
			IDLE: begin
				tx_line <= 1'b1;
				if (start_send) begin
					data_reg    <= data_byte;
					bit_counter <= 0;
				end
			end
			

			START: begin
				tx_line <= 1'b0;
			end

			DATA: begin
				tx_line <= data_reg[bit_counter];
				bit_counter <= bit_counter + 1;
			end


			STOP: begin
				tx_line <= 1'b1;
			end
		endcase
	end
end

always @(*) begin
	case (current_state)
		IDLE: next_state = start_send ? START : IDLE;
		START: next_state = DATA;
		DATA: next_state = (bit_counter == 7) ? STOP : DATA;
		STOP: next_state = IDLE;
		default: next_state = IDLE;
	endcase
end

endmodule

FSM/uart_tb.v
`timescale 1ns/1ps

module uart_tb;

	reg clk;
	reg rst;
	reg start_send;
	reg [7:0] data_byte;
	wire tx_line;

	uart uut (
		.clk(clk),
		.rst(rst),
		.start_send(start_send),
		.data_byte(data_byte),
		.tx_line(tx_line)
);

	initial begin 
		clk = 0;
	forever #5 clk = ~clk;
end

	initial begin
	$dumpfile("uart.vcd");
	$dumpvars(0, uart_tb);
	$monitor("%0t | clk=%b | rst=%b | start=%b | tx_line=%b |", $time, clk, rst, start_send, tx_line);

	rst = 1;
	start_send = 0;
	data_byte = 8'b00000000;

	#12 rst = 0;


	#8 data_byte = 8'b10110010;
	#2 start_send = 1;
	#10 start_send = 0;


	#150;

	$finish;
end

endmodule

FSM/uart.vcd
$date
	Mon Jul 27 00:13:38 2026
$end
$version
	Icarus Verilog
$end
$timescale
	1ps
$end
$scope module uart_tb $end
$var wire 1 ! tx_line $end
$var reg 1 " clk $end
$var reg 8 # data_byte [7:0] $end
$var reg 1 $ rst $end
$var reg 1 % start_send $end
$scope module uut $end
$var wire 1 " clk $end
$var wire 8 & data_byte [7:0] $end
$var wire 1 $ rst $end
$var wire 1 % start_send $end
$var parameter 2 ' DATA $end
$var parameter 2 ( IDLE $end
$var parameter 2 ) START $end
$var parameter 2 * STOP $end
$var reg 3 + bit_counter [2:0] $end
$var reg 2 , current_state [1:0] $end
$var reg 8 - data_reg [7:0] $end
$var reg 2 . next_state [1:0] $end
$var reg 1 ! tx_line $end
$upscope $end
$upscope $end
$enddefinitions $end
$comment Show the parameter values. $end
$dumpall
b11 *
b1 )
b0 (
b10 '
$end
#0
$dumpvars
b0 .
bx -
bx ,
bx +
b0 &
0%
1$
b0 #
0"
x!
$end
#5000
b0 ,
1!
b0 -
b0 +
1"
#10000
0"
#12000
0$
#15000
1"
#20000
0"
b10110010 #
b10110010 &
#22000
b1 .
1%
#25000
b10 .
b1 ,
b10110010 -
1"
#30000
0"
#32000
0%
#35000
0!
b10 ,
1"
#40000
0"
#45000
b1 +
1"
#50000
0"
#55000
b10 +
1!
1"
#60000
0"
#65000
b11 +
0!
1"
#70000
0"
#75000
b100 +
1"
#80000
0"
#85000
b101 +
1!
1"
#90000
0"
#95000
b110 +
1"
#100000
0"
#105000
b11 .
b111 +
0!
1"
#110000
0"
#115000
b0 .
b0 +
1!
b11 ,
1"
#120000
0"
#125000
b0 ,
1"
